{
  "$schema": "https://developer.microsoft.com/json-schemas/fabric/item/report/definition/visualContainer/2.0.0/schema.json",
  "name": "9123e4504e28a56213a0",
  "position": {
    "x": 440,
    "y": 558.88888888888891,
    "z": 8000,
    "height": 45.555555555555557,
    "width": 167.77777777777777,
    "tabOrder": 5000
  },
  "visual": {
    "visualType": "textbox",
    "objects": {
      "general": [
        {
          "properties": {
            "paragraphs": [
              {
                "textRuns": [
                  {
                    "value": "Tech",
                    "textStyle": {
                      "fontWeight": "bold",
                      "fontSize": "16pt",
                      "color": "#666666"
                    }
                  }
                ]
              }
            ]
          }
        }
      ]
    },
    "visualContainerObjects": {
      "background": [
        {
          "properties": {
            "show": {
              "expr": {
                "Literal": {
                  "Value": "false"
                }
              }
            }
          }
        }
      ]
    },
    "drillFilterOtherVisuals": true
  }
}